schematics/__init__.py
schematics/common.py
schematics/compat.py
schematics/datastructures.py
schematics/deprecated.py
schematics/exceptions.py
schematics/iteration.py
schematics/models.py
schematics/role.py
schematics/schema.py
schematics/transforms.py
schematics/translator.py
schematics/undefined.py
schematics/util.py
schematics/validate.py
schematics/contrib/__init__.py
schematics/contrib/enum_type.py
schematics/contrib/machine.py
schematics/contrib/mongo.py
schematics/types/__init__.py
schematics/types/base.py
schematics/types/compound.py
schematics/types/net.py
schematics/types/serializable.py
schematics/types/union.py
schematics_fork-2.1.1.dist-info/LICENSE
schematics_fork-2.1.1.dist-info/METADATA
schematics_fork-2.1.1.dist-info/WHEEL
schematics_fork-2.1.1.dist-info/top_level.txt
schematics_fork-2.1.1.dist-info/RECORD
