Metadata-Version: 2.1
Name: schematics-fork
Version: 2.1.1
Summary: Python Data Structures for Humans (forked for new release)
Home-page: https://github.com/MichaelAquilina/schematics
Author: James Dennis, Jökull Sólberg, Jóhann Þorvaldur Bergþórsson, Kalle Tuure, Paul Eipper
Author-email: jdennis@gmail.com, jokull@plainvanillagames.com, johann@plainvanillagames.com, kalle@goodtimes.fi, paul@nkey.com.br
License: BSD
Download-URL: https://github.com/schematics/schematics/archive/v2.1.1.tar.gz
Platform: UNKNOWN
Classifier: Intended Audience :: Developers
Classifier: License :: OSI Approved :: BSD License
Classifier: Programming Language :: Python
Classifier: Programming Language :: Python :: 2
Classifier: Programming Language :: Python :: 2.7
Classifier: Programming Language :: Python :: 3
Classifier: Programming Language :: Python :: 3.2
Classifier: Programming Language :: Python :: 3.3
Classifier: Programming Language :: Python :: 3.4
Classifier: Programming Language :: Python :: 3.5
Classifier: Programming Language :: Python :: 3.6
Classifier: Programming Language :: Python :: 3.7
